[
  {
    "id": "CARD_1",
    "url": "https://upload.wikimedia.org/wikipedia/commons/a/a2/Blackpink_Ros%C3%A9_Rimowa_2.jpg",
    "rarity": "Legendary",
    "name": "Photocard #1"
  },
  {
    "id": "CARD_2",
    "url": "https://upload.wikimedia.org/wikipedia/commons/7/70/20190518_Blackpink_Amsterdam_concert_23.jpg",
    "rarity": "Common",
    "name": "Photocard #2"
  },
  {
    "id": "CARD_3",
    "url": "https://upload.wikimedia.org/wikipedia/commons/3/3a/20190518_Blackpink_Amsterdam_concert_10.jpg",
    "rarity": "Common",
    "name": "Photocard #3"
  },
  {
    "id": "CARD_4",
    "url": "https://upload.wikimedia.org/wikipedia/commons/6/6e/Mamamoo_and_Blackpink_in_2016.jpg",
    "rarity": "Common",
    "name": "Photocard #4"
  },
  {
    "id": "CARD_5",
    "url": "https://upload.wikimedia.org/wikipedia/commons/e/ec/Blackpink_Born_Pink_Tour_Hanoi_01.jpg",
    "rarity": "Rare",
    "name": "Photocard #5"
  },
  {
    "id": "CARD_6",
    "url": "https://upload.wikimedia.org/wikipedia/commons/2/2d/Kim_Ji-Soo_in_2020_Dior_%289%29.png",
    "rarity": "Common",
    "name": "Photocard #6"
  },
  {
    "id": "CARD_7",
    "url": "https://upload.wikimedia.org/wikipedia/commons/d/d9/Kim_Jennie_%28%EA%B9%80%EC%A0%9C%EB%8B%88%29_02.png",
    "rarity": "Common",
    "name": "Photocard #7"
  },
  {
    "id": "CARD_8",
    "url": "https://upload.wikimedia.org/wikipedia/commons/e/e7/Kim_Ji-soo_at_Marie_Claire_Korea_photo_shooting_2020-08-13_%282%29.png",
    "rarity": "Common",
    "name": "Photocard #8"
  },
  {
    "id": "CARD_9",
    "url": "https://upload.wikimedia.org/wikipedia/commons/d/d5/20240314_Lisa_Manoban_05.jpg",
    "rarity": "Rare",
    "name": "Photocard #9"
  },
  {
    "id": "CARD_10",
    "url": "https://upload.wikimedia.org/wikipedia/commons/b/b4/170517_Kim_Ji-soo_Blackpink_03.jpg",
    "rarity": "Common",
    "name": "Photocard #10"
  },
  {
    "id": "CARD_11",
    "url": "https://upload.wikimedia.org/wikipedia/commons/d/d7/170517_Kim_Ji-soo_Blackpink_02.jpg",
    "rarity": "Epic",
    "name": "Photocard #11"
  },
  {
    "id": "CARD_12",
    "url": "https://upload.wikimedia.org/wikipedia/commons/7/7a/20260526_Jennie_Kim_04.jpg",
    "rarity": "Common",
    "name": "Photocard #12"
  },
  {
    "id": "CARD_13",
    "url": "https://upload.wikimedia.org/wikipedia/commons/d/da/Kim_Ji-soo_in_Sydney_on_June_15th%2C_2019_01.png",
    "rarity": "Rare",
    "name": "Photocard #13"
  },
  {
    "id": "CARD_14",
    "url": "https://upload.wikimedia.org/wikipedia/commons/9/93/Blackpink%27s_Lisa_Manoban_06.png",
    "rarity": "Common",
    "name": "Photocard #14"
  },
  {
    "id": "CARD_15",
    "url": "https://upload.wikimedia.org/wikipedia/commons/f/fb/Kim_Ji-Soo_in_2020_Dior_%2810%29.png",
    "rarity": "Common",
    "name": "Photocard #15"
  },
  {
    "id": "CARD_16",
    "url": "https://upload.wikimedia.org/wikipedia/commons/2/28/Kim_Ji-Soo_in_2020_Dior_%283%29.png",
    "rarity": "Common",
    "name": "Photocard #16"
  },
  {
    "id": "CARD_17",
    "url": "https://upload.wikimedia.org/wikipedia/commons/c/c6/20190518_Blackpink_Amsterdam_concert_09_Ros%C3%A9_and_Lisa.jpg",
    "rarity": "Rare",
    "name": "Photocard #17"
  },
  {
    "id": "CARD_18",
    "url": "https://upload.wikimedia.org/wikipedia/commons/0/0f/20190518_Blackpink_Amsterdam_concert_13.jpg",
    "rarity": "Common",
    "name": "Photocard #18"
  },
  {
    "id": "CARD_19",
    "url": "https://upload.wikimedia.org/wikipedia/commons/2/2a/BLACKPINK_Pink_Venom_Tour_2022_%2852544659735%29.jpg",
    "rarity": "Common",
    "name": "Photocard #19"
  },
  {
    "id": "CARD_20",
    "url": "https://upload.wikimedia.org/wikipedia/commons/9/93/BLACKPINK%27s_Lisa_for_BULGARI_June_2023_01.jpg",
    "rarity": "Common",
    "name": "Photocard #20"
  },
  {
    "id": "CARD_21",
    "url": "https://upload.wikimedia.org/wikipedia/commons/4/4b/Kim_Ji-Soo_in_2020_Dior_%2815%29.png",
    "rarity": "Legendary",
    "name": "Photocard #21"
  },
  {
    "id": "CARD_22",
    "url": "https://upload.wikimedia.org/wikipedia/commons/c/cb/Lalisa_Manobal_at_the_Busan_International_Film_Festival_2025_02.jpg",
    "rarity": "Common",
    "name": "Photocard #22"
  },
  {
    "id": "CARD_23",
    "url": "https://upload.wikimedia.org/wikipedia/commons/8/8c/170514_Jennie_Kim_at_YG_x_UNICEF_Walking_Festival_06.jpg",
    "rarity": "Common",
    "name": "Photocard #23"
  },
  {
    "id": "CARD_24",
    "url": "https://upload.wikimedia.org/wikipedia/commons/d/d9/20240314_Lisa_Manoban_06.jpg",
    "rarity": "Common",
    "name": "Photocard #24"
  },
  {
    "id": "CARD_25",
    "url": "https://upload.wikimedia.org/wikipedia/commons/f/f0/20240314_Lisa_Manoban_13.jpg",
    "rarity": "Rare",
    "name": "Photocard #25"
  },
  {
    "id": "CARD_26",
    "url": "https://upload.wikimedia.org/wikipedia/commons/7/72/Kim_Jennie_%28%EA%B9%80%EC%A0%9C%EB%8B%88%29_06.png",
    "rarity": "Common",
    "name": "Photocard #26"
  },
  {
    "id": "CARD_27",
    "url": "https://upload.wikimedia.org/wikipedia/commons/3/36/Blackpink_Barcelona_May_25_2019_%282%29.jpg",
    "rarity": "Common",
    "name": "Photocard #27"
  },
  {
    "id": "CARD_28",
    "url": "https://upload.wikimedia.org/wikipedia/commons/6/6c/190424_BLACKPINK_CHICAGO_CONCERT.jpg",
    "rarity": "Common",
    "name": "Photocard #28"
  },
  {
    "id": "CARD_29",
    "url": "https://upload.wikimedia.org/wikipedia/commons/7/73/BLACKPINK%27s_Lisa_for_BULGARI_June_2023_03.jpg",
    "rarity": "Rare",
    "name": "Photocard #29"
  },
  {
    "id": "CARD_30",
    "url": "https://upload.wikimedia.org/wikipedia/commons/0/02/20190518_Blackpink_Amsterdam_concert_17.jpg",
    "rarity": "Common",
    "name": "Photocard #30"
  },
  {
    "id": "CARD_31",
    "url": "https://upload.wikimedia.org/wikipedia/commons/2/23/20190106_%28NEWSEN%29_%EB%B8%94%EB%9E%99%ED%95%91%ED%81%AC%28BLACKPINK%29%2C_%EC%88%98%EC%A4%8D%EC%9D%80_%EB%A7%8E%EC%9D%80_%EC%86%8C%EB%85%80%EC%A7%80%EB%A7%8C_%EB%8F%8B%EB%B3%B4%EC%9D%B4%EB%8A%94_%EC%95%84%EB%A6%84%EB%8B%A4%EC%9A%B4_%EB%AF%B8%EB%AA%A8_%28Golden_Disc_Awards_2019%29_%284%29.jpg",
    "rarity": "Epic",
    "name": "Photocard #31"
  },
  {
    "id": "CARD_32",
    "url": "https://upload.wikimedia.org/wikipedia/commons/f/f7/Kim_Jennie_%28%EA%B9%80%EC%A0%9C%EB%8B%88%29_01.png",
    "rarity": "Common",
    "name": "Photocard #32"
  },
  {
    "id": "CARD_33",
    "url": "https://upload.wikimedia.org/wikipedia/commons/6/69/BLACKPINK_Pink_Venom_Tour_2022_%2852543715107%29.jpg",
    "rarity": "Rare",
    "name": "Photocard #33"
  },
  {
    "id": "CARD_34",
    "url": "https://upload.wikimedia.org/wikipedia/commons/d/d1/Blackpink_Born_Pink_Tour_Hanoi_02.jpg",
    "rarity": "Common",
    "name": "Photocard #34"
  },
  {
    "id": "CARD_35",
    "url": "https://upload.wikimedia.org/wikipedia/commons/1/18/20190518_Blackpink_Amsterdam_concert_20.jpg",
    "rarity": "Common",
    "name": "Photocard #35"
  },
  {
    "id": "CARD_36",
    "url": "https://upload.wikimedia.org/wikipedia/commons/9/90/20240314_Lisa_Manoban_01.jpg",
    "rarity": "Common",
    "name": "Photocard #36"
  },
  {
    "id": "CARD_37",
    "url": "https://upload.wikimedia.org/wikipedia/commons/2/25/20240314_Lisa_Manoban_04.jpg",
    "rarity": "Rare",
    "name": "Photocard #37"
  },
  {
    "id": "CARD_38",
    "url": "https://upload.wikimedia.org/wikipedia/commons/4/49/Blackpink%27s_Lisa_Manoban_05.jpg",
    "rarity": "Common",
    "name": "Photocard #38"
  },
  {
    "id": "CARD_39",
    "url": "https://upload.wikimedia.org/wikipedia/commons/9/96/BLACKPINK%27s_Lisa_for_BULGARI_June_2023_0.3.jpg",
    "rarity": "Common",
    "name": "Photocard #39"
  },
  {
    "id": "CARD_40",
    "url": "https://upload.wikimedia.org/wikipedia/commons/7/72/Kim_Jennie_%28%EA%B9%80%EC%A0%9C%EB%8B%88%29_03.png",
    "rarity": "Common",
    "name": "Photocard #40"
  },
  {
    "id": "CARD_41",
    "url": "https://upload.wikimedia.org/wikipedia/commons/b/b1/20240314_Lisa_Manoban_09.jpg",
    "rarity": "Legendary",
    "name": "Photocard #41"
  },
  {
    "id": "CARD_42",
    "url": "https://upload.wikimedia.org/wikipedia/commons/d/d5/Munch_Girls_on_the_pier.jpg",
    "rarity": "Common",
    "name": "Photocard #42"
  },
  {
    "id": "CARD_43",
    "url": "https://upload.wikimedia.org/wikipedia/commons/4/4f/Kim_Ji-Soo_in_2020_Dior_%281%29.png",
    "rarity": "Common",
    "name": "Photocard #43"
  },
  {
    "id": "CARD_44",
    "url": "https://upload.wikimedia.org/wikipedia/commons/5/52/Kim_Ji-soo_in_Sydney_on_June_15th%2C_2019_03.png",
    "rarity": "Common",
    "name": "Photocard #44"
  },
  {
    "id": "CARD_45",
    "url": "https://upload.wikimedia.org/wikipedia/commons/c/cf/20190518_Blackpink_Amsterdam_concert_37.jpg",
    "rarity": "Rare",
    "name": "Photocard #45"
  },
  {
    "id": "CARD_46",
    "url": "https://upload.wikimedia.org/wikipedia/commons/f/fe/BLACKPINK_Pink_Venom_Tour_2022_%2852544471474%29.jpg",
    "rarity": "Common",
    "name": "Photocard #46"
  },
  {
    "id": "CARD_47",
    "url": "https://upload.wikimedia.org/wikipedia/commons/c/c2/Kim_Ji-Soo_in_2020_Dior_%2810%29_%28cropped%29.png",
    "rarity": "Common",
    "name": "Photocard #47"
  },
  {
    "id": "CARD_48",
    "url": "https://upload.wikimedia.org/wikipedia/commons/a/a8/Kim_Jennie_%28%EA%B9%80%EC%A0%9C%EB%8B%88%29_07.png",
    "rarity": "Common",
    "name": "Photocard #48"
  },
  {
    "id": "CARD_49",
    "url": "https://upload.wikimedia.org/wikipedia/commons/7/78/BLACKPINK_Pink_Venom_Tour_2022_%2852544471174%29.jpg",
    "rarity": "Rare",
    "name": "Photocard #49"
  },
  {
    "id": "CARD_50",
    "url": "https://upload.wikimedia.org/wikipedia/commons/f/f0/20240314_Lisa_Manoban_14.jpg",
    "rarity": "Common",
    "name": "Photocard #50"
  },
  {
    "id": "CARD_51",
    "url": "https://upload.wikimedia.org/wikipedia/commons/2/22/Kim_Ji-Soo_in_2020_Dior_%285%29.png",
    "rarity": "Epic",
    "name": "Photocard #51"
  },
  {
    "id": "CARD_52",
    "url": "https://upload.wikimedia.org/wikipedia/commons/f/f6/221201_BLACKPINK_Born_Pink_Tour_London.jpg",
    "rarity": "Common",
    "name": "Photocard #52"
  },
  {
    "id": "CARD_53",
    "url": "https://upload.wikimedia.org/wikipedia/commons/2/2d/20260526_Jennie_Kim_01.jpg",
    "rarity": "Rare",
    "name": "Photocard #53"
  },
  {
    "id": "CARD_54",
    "url": "https://upload.wikimedia.org/wikipedia/commons/b/ba/Lalisa_Manobal_at_the_Busan_International_Film_Festival_2025_03.jpg",
    "rarity": "Common",
    "name": "Photocard #54"
  },
  {
    "id": "CARD_55",
    "url": "https://upload.wikimedia.org/wikipedia/commons/d/d9/20190518_Blackpink_Amsterdam_concert_44.jpg",
    "rarity": "Common",
    "name": "Photocard #55"
  },
  {
    "id": "CARD_56",
    "url": "https://upload.wikimedia.org/wikipedia/commons/9/9f/170514_Jennie_Kim_at_YG_x_UNICEF_Walking_Festival_04.jpg",
    "rarity": "Common",
    "name": "Photocard #56"
  },
  {
    "id": "CARD_57",
    "url": "https://upload.wikimedia.org/wikipedia/commons/0/01/BLACKPINK%27s_Lisa_for_BULGARI_June_2023_0.2.jpg",
    "rarity": "Rare",
    "name": "Photocard #57"
  },
  {
    "id": "CARD_58",
    "url": "https://upload.wikimedia.org/wikipedia/commons/1/13/BLACKPINK_Pink_Venom_Tour_2022_%2852544176071%29.jpg",
    "rarity": "Common",
    "name": "Photocard #58"
  },
  {
    "id": "CARD_59",
    "url": "https://upload.wikimedia.org/wikipedia/commons/0/09/Blackpink_Coachella_2023_02_%28cropped%29.jpg",
    "rarity": "Common",
    "name": "Photocard #59"
  },
  {
    "id": "CARD_60",
    "url": "https://upload.wikimedia.org/wikipedia/commons/3/31/BLACKPINK_Pink_Venom_Tour_2022_%2852544471309%29.jpg",
    "rarity": "Common",
    "name": "Photocard #60"
  },
  {
    "id": "CARD_61",
    "url": "https://upload.wikimedia.org/wikipedia/commons/c/cf/BLACKPINK%27s_Lisa_for_BULGARI_June_2023_04.jpg",
    "rarity": "Legendary",
    "name": "Photocard #61"
  },
  {
    "id": "CARD_62",
    "url": "https://upload.wikimedia.org/wikipedia/commons/9/93/20240314_Lisa_Manoban_11.jpg",
    "rarity": "Common",
    "name": "Photocard #62"
  },
  {
    "id": "CARD_63",
    "url": "https://upload.wikimedia.org/wikipedia/commons/0/06/Young_Girls_Strike_a_Pose_-_Busua_-_Ghana_%284737816187%29.jpg",
    "rarity": "Common",
    "name": "Photocard #63"
  },
  {
    "id": "CARD_64",
    "url": "https://upload.wikimedia.org/wikipedia/commons/1/1d/20190518_Blackpink_Amsterdam_concert_36.jpg",
    "rarity": "Common",
    "name": "Photocard #64"
  },
  {
    "id": "CARD_65",
    "url": "https://upload.wikimedia.org/wikipedia/commons/6/68/20240314_Lisa_Manoban_10.jpg",
    "rarity": "Rare",
    "name": "Photocard #65"
  },
  {
    "id": "CARD_66",
    "url": "https://upload.wikimedia.org/wikipedia/commons/5/57/170514_Jennie_Kim_at_YG_x_UNICEF_Walking_Festival_12.jpg",
    "rarity": "Common",
    "name": "Photocard #66"
  },
  {
    "id": "CARD_67",
    "url": "https://upload.wikimedia.org/wikipedia/commons/3/35/Kim_Jennie_%28%EA%B9%80%EC%A0%9C%EB%8B%88%29_04.jpg",
    "rarity": "Common",
    "name": "Photocard #67"
  },
  {
    "id": "CARD_68",
    "url": "https://upload.wikimedia.org/wikipedia/commons/c/c1/Kim_Ji-Soo_in_2020_Dior_%288%29.png",
    "rarity": "Common",
    "name": "Photocard #68"
  },
  {
    "id": "CARD_69",
    "url": "https://upload.wikimedia.org/wikipedia/commons/1/13/20190518_Blackpink_Amsterdam_concert_08.jpg",
    "rarity": "Rare",
    "name": "Photocard #69"
  },
  {
    "id": "CARD_70",
    "url": "https://upload.wikimedia.org/wikipedia/commons/7/71/20190518_Blackpink_Amsterdam_concert_06.jpg",
    "rarity": "Common",
    "name": "Photocard #70"
  },
  {
    "id": "CARD_71",
    "url": "https://upload.wikimedia.org/wikipedia/commons/6/6d/170514_Jennie_Kim_at_YG_x_UNICEF_Walking_Festival_09.jpg",
    "rarity": "Epic",
    "name": "Photocard #71"
  },
  {
    "id": "CARD_72",
    "url": "https://upload.wikimedia.org/wikipedia/commons/2/26/20190518_Blackpink_Amsterdam_concert_30.jpg",
    "rarity": "Common",
    "name": "Photocard #72"
  },
  {
    "id": "CARD_73",
    "url": "https://upload.wikimedia.org/wikipedia/commons/d/da/Kim_Ji-Soo_in_2020_Dior_%286%29.png",
    "rarity": "Rare",
    "name": "Photocard #73"
  },
  {
    "id": "CARD_74",
    "url": "https://upload.wikimedia.org/wikipedia/commons/a/aa/170517_Kim_Ji-soo_Blackpink_06.jpg",
    "rarity": "Common",
    "name": "Photocard #74"
  },
  {
    "id": "CARD_75",
    "url": "https://upload.wikimedia.org/wikipedia/commons/5/59/20260526_Jennie_Kim_09.jpg",
    "rarity": "Common",
    "name": "Photocard #75"
  },
  {
    "id": "CARD_76",
    "url": "https://upload.wikimedia.org/wikipedia/commons/1/1d/20190518_Blackpink_Amsterdam_concert_18.jpg",
    "rarity": "Common",
    "name": "Photocard #76"
  },
  {
    "id": "CARD_77",
    "url": "https://upload.wikimedia.org/wikipedia/commons/4/46/20240314_Lisa_Manoban_03.jpg",
    "rarity": "Rare",
    "name": "Photocard #77"
  },
  {
    "id": "CARD_78",
    "url": "https://upload.wikimedia.org/wikipedia/commons/1/12/20190518_Blackpink_Amsterdam_concert_11.jpg",
    "rarity": "Common",
    "name": "Photocard #78"
  },
  {
    "id": "CARD_79",
    "url": "https://upload.wikimedia.org/wikipedia/commons/d/d2/Kim_Ji-su_from_acrofan.jpg",
    "rarity": "Common",
    "name": "Photocard #79"
  },
  {
    "id": "CARD_80",
    "url": "https://upload.wikimedia.org/wikipedia/commons/a/a9/170517_Jennie_Kim_Blackpink_05.jpg",
    "rarity": "Common",
    "name": "Photocard #80"
  },
  {
    "id": "CARD_81",
    "url": "https://upload.wikimedia.org/wikipedia/commons/b/b3/20190518_Blackpink_Amsterdam_concert_22_%28cropped%29.jpg",
    "rarity": "Legendary",
    "name": "Photocard #81"
  },
  {
    "id": "CARD_82",
    "url": "https://upload.wikimedia.org/wikipedia/commons/e/e4/BLACKPINK_Pink_Venom_Tour_2022_%281%29.jpg",
    "rarity": "Common",
    "name": "Photocard #82"
  },
  {
    "id": "CARD_83",
    "url": "https://upload.wikimedia.org/wikipedia/commons/2/22/Blackpink%27s_Lisa_Manoban_10.png",
    "rarity": "Common",
    "name": "Photocard #83"
  },
  {
    "id": "CARD_84",
    "url": "https://upload.wikimedia.org/wikipedia/commons/0/06/BLACKPINK%27s_Lisa_for_BULGARI_June_2023_0.4.jpg",
    "rarity": "Common",
    "name": "Photocard #84"
  },
  {
    "id": "CARD_85",
    "url": "https://upload.wikimedia.org/wikipedia/commons/5/50/20240314_Lisa_Manoban_08.jpg",
    "rarity": "Rare",
    "name": "Photocard #85"
  },
  {
    "id": "CARD_86",
    "url": "https://upload.wikimedia.org/wikipedia/commons/1/15/20190518_Blackpink_Amsterdam_concert_34.jpg",
    "rarity": "Common",
    "name": "Photocard #86"
  },
  {
    "id": "CARD_87",
    "url": "https://upload.wikimedia.org/wikipedia/commons/3/38/Blackpink_Coachella_2023_02.jpg",
    "rarity": "Common",
    "name": "Photocard #87"
  },
  {
    "id": "CARD_88",
    "url": "https://upload.wikimedia.org/wikipedia/commons/5/5f/Blackpink_Coachella_2023_01.jpg",
    "rarity": "Common",
    "name": "Photocard #88"
  },
  {
    "id": "CARD_89",
    "url": "https://upload.wikimedia.org/wikipedia/commons/8/8e/Kim_Ji-Soo_in_2020_Dior_%284%29.png",
    "rarity": "Rare",
    "name": "Photocard #89"
  },
  {
    "id": "CARD_90",
    "url": "https://upload.wikimedia.org/wikipedia/commons/7/7f/Lisa_Lalisa_Manobal_at_Emmys_2025.jpg",
    "rarity": "Common",
    "name": "Photocard #90"
  },
  {
    "id": "CARD_91",
    "url": "https://upload.wikimedia.org/wikipedia/commons/c/c1/20190518_Blackpink_Amsterdam_concert_01.jpg",
    "rarity": "Epic",
    "name": "Photocard #91"
  },
  {
    "id": "CARD_92",
    "url": "https://upload.wikimedia.org/wikipedia/commons/d/d6/20190518_Blackpink_Amsterdam_concert_33.jpg",
    "rarity": "Common",
    "name": "Photocard #92"
  },
  {
    "id": "CARD_93",
    "url": "https://upload.wikimedia.org/wikipedia/commons/d/dc/BLACKPINK_Pink_Venom_Tour_2022.jpg",
    "rarity": "Rare",
    "name": "Photocard #93"
  },
  {
    "id": "CARD_94",
    "url": "https://upload.wikimedia.org/wikipedia/commons/b/b3/Blackpink_Ros%C3%A9_Rimowa_1.jpg",
    "rarity": "Common",
    "name": "Photocard #94"
  },
  {
    "id": "CARD_95",
    "url": "https://upload.wikimedia.org/wikipedia/commons/b/b8/20190518_Blackpink_Amsterdam_concert_21.jpg",
    "rarity": "Common",
    "name": "Photocard #95"
  },
  {
    "id": "CARD_96",
    "url": "https://upload.wikimedia.org/wikipedia/commons/4/43/Girl_of_the_Welayta_people.jpg",
    "rarity": "Common",
    "name": "Photocard #96"
  },
  {
    "id": "CARD_97",
    "url": "https://upload.wikimedia.org/wikipedia/commons/c/cd/Lalisa_Manobal_at_the_Busan_International_Film_Festival_2025_01.jpg",
    "rarity": "Rare",
    "name": "Photocard #97"
  },
  {
    "id": "CARD_98",
    "url": "https://upload.wikimedia.org/wikipedia/commons/2/27/Kim_Ji-Soo_in_2020_Dior_%2813%29.png",
    "rarity": "Common",
    "name": "Photocard #98"
  },
  {
    "id": "CARD_99",
    "url": "https://upload.wikimedia.org/wikipedia/commons/8/8d/BLACKPINK%27s_Lisa_for_BULGARI_June_2023_02.jpg",
    "rarity": "Common",
    "name": "Photocard #99"
  },
  {
    "id": "CARD_100",
    "url": "https://upload.wikimedia.org/wikipedia/commons/f/fa/Kim_Ji-soo_in_Sydney_on_June_15th%2C_2019_02.png",
    "rarity": "Common",
    "name": "Photocard #100"
  },
  {
    "id": "CARD_101",
    "url": "https://upload.wikimedia.org/wikipedia/commons/1/1c/20240314_Lisa_Manoban_12.jpg",
    "rarity": "Legendary",
    "name": "Photocard #101"
  },
  {
    "id": "CARD_102",
    "url": "https://upload.wikimedia.org/wikipedia/commons/d/d8/20260526_Jennie_Kim_02.jpg",
    "rarity": "Common",
    "name": "Photocard #102"
  },
  {
    "id": "CARD_103",
    "url": "https://upload.wikimedia.org/wikipedia/commons/f/fe/170514_Jennie_Kim_at_YG_x_UNICEF_Walking_Festival_11.jpg",
    "rarity": "Common",
    "name": "Photocard #103"
  },
  {
    "id": "CARD_104",
    "url": "https://upload.wikimedia.org/wikipedia/commons/f/fa/20190518_Blackpink_Amsterdam_concert_24.jpg",
    "rarity": "Common",
    "name": "Photocard #104"
  },
  {
    "id": "CARD_105",
    "url": "https://upload.wikimedia.org/wikipedia/commons/4/45/20190518_Blackpink_Amsterdam_concert_07.jpg",
    "rarity": "Rare",
    "name": "Photocard #105"
  },
  {
    "id": "CARD_106",
    "url": "https://upload.wikimedia.org/wikipedia/commons/1/17/20190518_Blackpink_Amsterdam_concert_31.jpg",
    "rarity": "Common",
    "name": "Photocard #106"
  },
  {
    "id": "CARD_107",
    "url": "https://upload.wikimedia.org/wikipedia/commons/f/fa/Blackpink_Lisa_at_Bvulgari_Avrora_Awards_2022.png",
    "rarity": "Common",
    "name": "Photocard #107"
  },
  {
    "id": "CARD_108",
    "url": "https://upload.wikimedia.org/wikipedia/commons/a/a7/BLACKPINK_Pink_Venom_Tour_2022_%2852544176156%29.jpg",
    "rarity": "Common",
    "name": "Photocard #108"
  },
  {
    "id": "CARD_109",
    "url": "https://upload.wikimedia.org/wikipedia/commons/f/ff/20190518_Blackpink_Amsterdam_concert_28.jpg",
    "rarity": "Rare",
    "name": "Photocard #109"
  },
  {
    "id": "CARD_110",
    "url": "https://upload.wikimedia.org/wikipedia/commons/8/86/Ros%C3%A9_BLACKPINK_PUBG_Mobile_Sept_2020_ad.png",
    "rarity": "Common",
    "name": "Photocard #110"
  },
  {
    "id": "CARD_111",
    "url": "https://upload.wikimedia.org/wikipedia/commons/1/1b/Kim_Jennie_%28%EA%B9%80%EC%A0%9C%EB%8B%88%29_05.jpg",
    "rarity": "Epic",
    "name": "Photocard #111"
  },
  {
    "id": "CARD_112",
    "url": "https://upload.wikimedia.org/wikipedia/commons/0/0d/Jennie_Kim_on_the_stage_in_2026.jpg",
    "rarity": "Common",
    "name": "Photocard #112"
  },
  {
    "id": "CARD_113",
    "url": "https://upload.wikimedia.org/wikipedia/commons/e/ed/BLACKPINK_Pink_Venom_Tour_2022_%283%29.jpg",
    "rarity": "Rare",
    "name": "Photocard #113"
  },
  {
    "id": "CARD_114",
    "url": "https://upload.wikimedia.org/wikipedia/commons/2/20/20260526_Jennie_Kim_08.jpg",
    "rarity": "Common",
    "name": "Photocard #114"
  },
  {
    "id": "CARD_115",
    "url": "https://upload.wikimedia.org/wikipedia/commons/1/1d/20190518_Blackpink_Amsterdam_concert_29.jpg",
    "rarity": "Common",
    "name": "Photocard #115"
  },
  {
    "id": "CARD_116",
    "url": "https://upload.wikimedia.org/wikipedia/commons/b/b9/BLACKPINK_%28%EB%B8%94%EB%9E%99%ED%95%91%ED%81%AC%29_Airport_Departure_Aug_25%2C_2022_%281%29.jpg",
    "rarity": "Common",
    "name": "Photocard #116"
  },
  {
    "id": "CARD_117",
    "url": "https://upload.wikimedia.org/wikipedia/commons/a/ae/20240314_Lisa_Manoban_07.jpg",
    "rarity": "Rare",
    "name": "Photocard #117"
  },
  {
    "id": "CARD_118",
    "url": "https://upload.wikimedia.org/wikipedia/commons/f/f9/170517_Kim_Ji-soo_Blackpink_04.jpg",
    "rarity": "Common",
    "name": "Photocard #118"
  },
  {
    "id": "CARD_119",
    "url": "https://upload.wikimedia.org/wikipedia/commons/1/1b/20240314_Lisa_Manoban_02.jpg",
    "rarity": "Common",
    "name": "Photocard #119"
  },
  {
    "id": "CARD_120",
    "url": "https://upload.wikimedia.org/wikipedia/commons/7/72/Dancing_Girls_Bath_%28Hampi_water_tank%29%2C_Hampi%2C_Vijayanagara%2C_Karnataka%2C_India_%282012%29.jpg",
    "rarity": "Common",
    "name": "Photocard #120"
  },
  {
    "id": "CARD_121",
    "url": "https://upload.wikimedia.org/wikipedia/commons/c/c1/BLACKPINK_%28%EB%B8%94%EB%9E%99%ED%95%91%ED%81%AC%29_Airport_Departure_Aug_25%2C_2022_%282%29.jpg",
    "rarity": "Legendary",
    "name": "Photocard #121"
  },
  {
    "id": "CARD_122",
    "url": "https://upload.wikimedia.org/wikipedia/commons/7/74/20190518_Blackpink_Amsterdam_concert_27.jpg",
    "rarity": "Common",
    "name": "Photocard #122"
  },
  {
    "id": "CARD_123",
    "url": "https://upload.wikimedia.org/wikipedia/commons/b/bf/20190518_Blackpink_Amsterdam_concert_46.jpg",
    "rarity": "Common",
    "name": "Photocard #123"
  },
  {
    "id": "CARD_124",
    "url": "https://upload.wikimedia.org/wikipedia/commons/6/61/Kim_Ji-soo_in_Sydney_on_June_15th%2C_2019_05.png",
    "rarity": "Common",
    "name": "Photocard #124"
  },
  {
    "id": "CARD_125",
    "url": "https://upload.wikimedia.org/wikipedia/commons/1/10/20190518_Blackpink_Amsterdam_concert_02.jpg",
    "rarity": "Rare",
    "name": "Photocard #125"
  },
  {
    "id": "CARD_126",
    "url": "https://upload.wikimedia.org/wikipedia/commons/1/14/20190518_Blackpink_Amsterdam_concert_04.jpg",
    "rarity": "Common",
    "name": "Photocard #126"
  },
  {
    "id": "CARD_127",
    "url": "https://upload.wikimedia.org/wikipedia/commons/d/d4/20190518_Blackpink_Amsterdam_concert_12.jpg",
    "rarity": "Common",
    "name": "Photocard #127"
  },
  {
    "id": "CARD_128",
    "url": "https://upload.wikimedia.org/wikipedia/commons/3/36/170514_Jennie_Kim_at_YG_x_UNICEF_Walking_Festival_10.jpg",
    "rarity": "Common",
    "name": "Photocard #128"
  },
  {
    "id": "CARD_129",
    "url": "https://upload.wikimedia.org/wikipedia/commons/9/9d/BLACKPINK_Pink_Venom_Tour_2022_%2852544724613%29.jpg",
    "rarity": "Rare",
    "name": "Photocard #129"
  },
  {
    "id": "CARD_130",
    "url": "https://upload.wikimedia.org/wikipedia/commons/c/ca/Lalisa_Manobal_at_the_Busan_International_Film_Festival_2025_05.jpg",
    "rarity": "Common",
    "name": "Photocard #130"
  },
  {
    "id": "CARD_131",
    "url": "https://upload.wikimedia.org/wikipedia/commons/5/57/Blackpink%27s_Lisa_Manoban_03.jpg",
    "rarity": "Epic",
    "name": "Photocard #131"
  },
  {
    "id": "CARD_132",
    "url": "https://upload.wikimedia.org/wikipedia/commons/e/e8/20190518_Blackpink_Amsterdam_concert_14.jpg",
    "rarity": "Common",
    "name": "Photocard #132"
  },
  {
    "id": "CARD_133",
    "url": "https://upload.wikimedia.org/wikipedia/commons/5/5b/Ros%C3%A9-On_the_Ground-logo.png",
    "rarity": "Rare",
    "name": "Photocard #133"
  },
  {
    "id": "CARD_134",
    "url": "https://upload.wikimedia.org/wikipedia/commons/b/b7/Kim_Ji-Soo_in_2020_Dior_%2812%29.png",
    "rarity": "Common",
    "name": "Photocard #134"
  },
  {
    "id": "CARD_135",
    "url": "https://upload.wikimedia.org/wikipedia/commons/7/77/Kim_Ji-Soo_in_2020_Dior_%282%29.png",
    "rarity": "Common",
    "name": "Photocard #135"
  },
  {
    "id": "CARD_136",
    "url": "https://upload.wikimedia.org/wikipedia/commons/8/88/20190518_Blackpink_Amsterdam_concert_26.jpg",
    "rarity": "Common",
    "name": "Photocard #136"
  },
  {
    "id": "CARD_137",
    "url": "https://upload.wikimedia.org/wikipedia/commons/c/cc/Kim_Ji-Soo_in_2020_Dior_%283%29_%28cropped%29.png",
    "rarity": "Rare",
    "name": "Photocard #137"
  },
  {
    "id": "CARD_138",
    "url": "https://upload.wikimedia.org/wikipedia/commons/2/25/BLACKPINK_Pink_Venom_Tour_2022_%282%29.jpg",
    "rarity": "Common",
    "name": "Photocard #138"
  },
  {
    "id": "CARD_139",
    "url": "https://upload.wikimedia.org/wikipedia/commons/f/f9/Kim_Ji-soo_in_Sydney_on_June_15th%2C_2019_04.png",
    "rarity": "Common",
    "name": "Photocard #139"
  },
  {
    "id": "CARD_140",
    "url": "https://upload.wikimedia.org/wikipedia/commons/2/29/170517_Kim_Ji-soo_Blackpink_01.jpg",
    "rarity": "Common",
    "name": "Photocard #140"
  },
  {
    "id": "CARD_141",
    "url": "https://upload.wikimedia.org/wikipedia/commons/b/bf/Blackpink_Born_Pink_Tour_Hanoi_03.jpg",
    "rarity": "Legendary",
    "name": "Photocard #141"
  },
  {
    "id": "CARD_142",
    "url": "https://upload.wikimedia.org/wikipedia/commons/e/ec/Mona_Lisa%2C_by_Leonardo_da_Vinci%2C_from_C2RMF_retouched.jpg",
    "rarity": "Common",
    "name": "Photocard #142"
  },
  {
    "id": "CARD_143",
    "url": "https://upload.wikimedia.org/wikipedia/commons/b/b1/Kim_Ji-Soo_in_2020_PUBG_%282%29.png",
    "rarity": "Common",
    "name": "Photocard #143"
  },
  {
    "id": "CARD_144",
    "url": "https://upload.wikimedia.org/wikipedia/commons/f/fa/Kim_Ji-Soo_in_2020_Dior_%2814%29.png",
    "rarity": "Common",
    "name": "Photocard #144"
  },
  {
    "id": "CARD_145",
    "url": "https://upload.wikimedia.org/wikipedia/commons/0/0f/221120_Ros%C3%A9_%E2%80%9CHard_to_Love%E2%80%9D_during_Born_Pink_World_Tour.jpg",
    "rarity": "Rare",
    "name": "Photocard #145"
  },
  {
    "id": "CARD_146",
    "url": "https://upload.wikimedia.org/wikipedia/commons/2/21/Ros%C3%A9_at_a_fan_signing_event_on_September_25%2C_2022.jpg",
    "rarity": "Common",
    "name": "Photocard #146"
  },
  {
    "id": "CARD_147",
    "url": "https://upload.wikimedia.org/wikipedia/commons/1/1e/20260526_Jennie_Kim_06.jpg",
    "rarity": "Common",
    "name": "Photocard #147"
  },
  {
    "id": "CARD_148",
    "url": "https://upload.wikimedia.org/wikipedia/commons/6/66/Blackpink_Lisa_GMP_240622.png",
    "rarity": "Common",
    "name": "Photocard #148"
  },
  {
    "id": "CARD_149",
    "url": "https://upload.wikimedia.org/wikipedia/commons/3/3c/Blackpink%27s_Lisa_Manoban_08.jpg",
    "rarity": "Rare",
    "name": "Photocard #149"
  },
  {
    "id": "CARD_150",
    "url": "https://upload.wikimedia.org/wikipedia/commons/c/c2/Kim_Ji-Soo_in_2020_Dior_%287%29.png",
    "rarity": "Common",
    "name": "Photocard #150"
  },
  {
    "id": "CARD_151",
    "url": "https://upload.wikimedia.org/wikipedia/commons/3/3b/Kim_Ji-soo_%28born_Yang_Sung-yoon_on_October_24%2C_1972%29_from_acrofan.jpg",
    "rarity": "Epic",
    "name": "Photocard #151"
  },
  {
    "id": "CARD_152",
    "url": "https://upload.wikimedia.org/wikipedia/commons/2/2e/BLACKPINK_Pink_Venom_Tour_2022_%2852543715232%29.jpg",
    "rarity": "Common",
    "name": "Photocard #152"
  },
  {
    "id": "CARD_153",
    "url": "https://upload.wikimedia.org/wikipedia/commons/b/bd/Kim_Ji-Soo_in_2020_Dior_%2811%29.png",
    "rarity": "Rare",
    "name": "Photocard #153"
  },
  {
    "id": "CARD_154",
    "url": "https://upload.wikimedia.org/wikipedia/commons/3/3e/170517_Kim_Ji-soo_Blackpink_05.jpg",
    "rarity": "Common",
    "name": "Photocard #154"
  },
  {
    "id": "CARD_155",
    "url": "https://upload.wikimedia.org/wikipedia/commons/2/23/Blackpink%27s_Lisa_Manoban_04.jpg",
    "rarity": "Common",
    "name": "Photocard #155"
  },
  {
    "id": "CARD_156",
    "url": "https://upload.wikimedia.org/wikipedia/commons/b/ba/Kim_Ji-Soo_in_2020_PUBG_%281%29.png",
    "rarity": "Common",
    "name": "Photocard #156"
  },
  {
    "id": "CARD_157",
    "url": "https://upload.wikimedia.org/wikipedia/commons/f/f1/Apt._%28Ros%C3%A9_and_Bruno_Mars_logo%29.png",
    "rarity": "Rare",
    "name": "Photocard #157"
  },
  {
    "id": "CARD_158",
    "url": "https://upload.wikimedia.org/wikipedia/commons/5/54/Blackpink%27s_Lisa_Manoban_02.png",
    "rarity": "Common",
    "name": "Photocard #158"
  },
  {
    "id": "CARD_159",
    "url": "https://upload.wikimedia.org/wikipedia/commons/8/89/20260526_Jennie_Kim_07.jpg",
    "rarity": "Common",
    "name": "Photocard #159"
  },
  {
    "id": "CARD_160",
    "url": "https://upload.wikimedia.org/wikipedia/commons/6/61/170514_Jennie_Kim_at_YG_x_UNICEF_Walking_Festival_08.jpg",
    "rarity": "Common",
    "name": "Photocard #160"
  },
  {
    "id": "CARD_161",
    "url": "https://upload.wikimedia.org/wikipedia/commons/a/a7/170514_Jennie_Kim_at_YG_x_UNICEF_Walking_Festival_13.jpg",
    "rarity": "Legendary",
    "name": "Photocard #161"
  },
  {
    "id": "CARD_162",
    "url": "https://upload.wikimedia.org/wikipedia/commons/a/a0/Mia_Rose_%28Singer%29.jpg",
    "rarity": "Common",
    "name": "Photocard #162"
  },
  {
    "id": "CARD_163",
    "url": "https://upload.wikimedia.org/wikipedia/commons/4/4f/Lalisa_Manobal_at_the_Busan_International_Film_Festival_2025_04.jpg",
    "rarity": "Common",
    "name": "Photocard #163"
  },
  {
    "id": "CARD_164",
    "url": "https://upload.wikimedia.org/wikipedia/commons/4/4b/170514_Jennie_Kim_at_YG_x_UNICEF_Walking_Festival_05.jpg",
    "rarity": "Common",
    "name": "Photocard #164"
  },
  {
    "id": "CARD_165",
    "url": "https://upload.wikimedia.org/wikipedia/commons/1/1b/WInd_Rose_Aguiar.png",
    "rarity": "Rare",
    "name": "Photocard #165"
  },
  {
    "id": "CARD_166",
    "url": "https://upload.wikimedia.org/wikipedia/commons/8/88/171001_%EC%BD%94%EB%A6%AC%EC%95%84_%EB%AE%A4%EC%A7%81_%ED%8E%98%EC%8A%A4%ED%8B%B0%EB%B2%8C_%EB%B8%94%EB%9E%99%ED%95%91%ED%81%AC_%281%29.jpg",
    "rarity": "Common",
    "name": "Photocard #166"
  },
  {
    "id": "CARD_167",
    "url": "https://upload.wikimedia.org/wikipedia/commons/e/ef/Rose_R_album_-_logo.png",
    "rarity": "Common",
    "name": "Photocard #167"
  },
  {
    "id": "CARD_168",
    "url": "https://upload.wikimedia.org/wikipedia/commons/9/95/170514_Jennie_Kim_at_YG_x_UNICEF_Walking_Festival_02.jpg",
    "rarity": "Common",
    "name": "Photocard #168"
  },
  {
    "id": "CARD_169",
    "url": "https://upload.wikimedia.org/wikipedia/commons/b/bc/20260526_Jennie_Kim_10.jpg",
    "rarity": "Rare",
    "name": "Photocard #169"
  },
  {
    "id": "CARD_170",
    "url": "https://upload.wikimedia.org/wikipedia/commons/2/2d/20260526_Jennie_Kim_03.jpg",
    "rarity": "Common",
    "name": "Photocard #170"
  },
  {
    "id": "CARD_171",
    "url": "https://upload.wikimedia.org/wikipedia/commons/5/56/Blackpink%27s_Lisa_Manoban_01.png",
    "rarity": "Epic",
    "name": "Photocard #171"
  },
  {
    "id": "CARD_172",
    "url": "https://upload.wikimedia.org/wikipedia/commons/d/dd/Blackpink%27s_Lisa_Manoban_11.png",
    "rarity": "Common",
    "name": "Photocard #172"
  },
  {
    "id": "CARD_173",
    "url": "https://upload.wikimedia.org/wikipedia/commons/0/07/20260526_Jennie_Kim_05.jpg",
    "rarity": "Rare",
    "name": "Photocard #173"
  },
  {
    "id": "CARD_174",
    "url": "https://upload.wikimedia.org/wikipedia/commons/7/74/20240314_Lisa_Manoban_12_%28cropped%29.jpg",
    "rarity": "Common",
    "name": "Photocard #174"
  },
  {
    "id": "CARD_175",
    "url": "https://upload.wikimedia.org/wikipedia/commons/c/cb/170514_Jennie_Kim_at_YG_x_UNICEF_Walking_Festival_01.jpg",
    "rarity": "Common",
    "name": "Photocard #175"
  },
  {
    "id": "CARD_176",
    "url": "https://upload.wikimedia.org/wikipedia/commons/7/7f/20190106_%28NEWSEN%29_%EB%B8%94%EB%9E%99%ED%95%91%ED%81%AC%28BLACKPINK%29%2C_%EC%88%98%EC%A4%8D%EC%9D%80_%EB%A7%8E%EC%9D%80_%EC%86%8C%EB%85%80%EC%A7%80%EB%A7%8C_%EB%8F%8B%EB%B3%B4%EC%9D%B4%EB%8A%94_%EC%95%84%EB%A6%84%EB%8B%A4%EC%9A%B4_%EB%AF%B8%EB%AA%A8_%28Golden_Disc_Awards_2019%29_%283%29.jpg",
    "rarity": "Common",
    "name": "Photocard #176"
  },
  {
    "id": "CARD_177",
    "url": "https://upload.wikimedia.org/wikipedia/commons/e/eb/Blackpink%27s_Lisa_Manoban_07.png",
    "rarity": "Rare",
    "name": "Photocard #177"
  },
  {
    "id": "CARD_178",
    "url": "https://upload.wikimedia.org/wikipedia/commons/6/69/221120_Ros%C3%A9_%E2%80%9CHard_to_Love%E2%80%9D_during_Born_Pink_World_Tour_%28cropped%29.jpg",
    "rarity": "Common",
    "name": "Photocard #178"
  },
  {
    "id": "CARD_179",
    "url": "https://upload.wikimedia.org/wikipedia/commons/3/33/Blackpink%27s_Lisa_Manoban_09.png",
    "rarity": "Common",
    "name": "Photocard #179"
  },
  {
    "id": "CARD_180",
    "url": "https://upload.wikimedia.org/wikipedia/commons/a/a4/Kim_Ji-soo_in_Sydney_on_June_15th%2C_2019_06.png",
    "rarity": "Common",
    "name": "Photocard #180"
  }
]